Workbook

Sheet Detail
A1: Monthly Project Budget
A2: Applicant Organization: | C2: Expense Type | D2: Description
A3: Applicant Full Name: | C3: Supplies | D3: Supplies or materials associated with manufacturing or analytical laboratory testing, costing less than $10,000 per item and having a useful life of 1 year or less
C4: Contractual | D4: Payments to vendors for manufacturing, testing, consulting services, or other similar third-party project expenses
C5: Other | D5: All other expenses that do not fit into the above categories
A6: Instructions:
A7: 1) Only populate green cells with your project budget; all other cells and rows are locked to prevent editing. Contact biolaunch@theari.us with questions.
A8: 2) The Total Amount should equal the total grant funds requested in your application (e.g., an amount between $50,000 and $500,000).
A9: 3) Expenses should reflect those to be paid by the Applicant Organization. For example, Applicant Organization personnel expenses are not eligible for BioCAN Grants,
A10: but a vendor's labor expenses to provide 3rd party services should show as Contractual expenses to the Applicant Organization.
A11: Vendor Name | B11: Activity Description | C11: Expense Type | D11: Total Amount | E11: Month 1 | F11: Month 2 | G11: Month 3 | H11: Month 4 | I11: Month 5 | J11: Month 6 | K11: Month 7 | L11: Month 8 | M11: Month 9 | N11: Month 10 | O11: Month 11 | P11: Month 12
C12: TOTAL | D12: =SUM(E12:P12) -> 0 | E12: =SUM(E13:E99) -> 0 | F12: =SUM(F13:F99) -> 0 | G12: =SUM(G13:G99) -> 0 | H12: =SUM(H13:H99) -> 0 | I12: =SUM(I13:I99) -> 0 | J12: =SUM(J13:J99) -> 0 | K12: =SUM(K13:K99) -> 0 | L12: =SUM(L13:L99) -> 0 | ... P12: =SUM(P13:P99) -> 0
D13: =SUM(E13:P13) -> 0
D14: =SUM(E14:P14) -> 0
D15: =SUM(E15:P15) -> 0
D16: =SUM(E16:P16) -> 0
D17: =SUM(E17:P17) -> 0
D18: =SUM(E18:P18) -> 0
D19: =SUM(E19:P19) -> 0
D20: =SUM(E20:P20) -> 0
D21: =SUM(E21:P21) -> 0
D22: =SUM(E22:P22) -> 0
D23: =SUM(E23:P23) -> 0
D24: =SUM(E24:P24) -> 0
... D99: =SUM(E99:P99) -> 0

Sheet Summary
A1: SECTION I - BUDGET INFORMATION
A2: The following is the Authorized Budget for this award. Reference section III - Specific Award Conditions for conditions related to the Authorized Budget.
A4: Proposed Budget
A5: Estimated Funding ($) | B5: Proposed | C5: Approved
A6: Federal Share (EDA Amount) | B6: =B21 -> 0 | C6: =C21 -> 0
A7: Non-Federal Matching Share | B7: 0 | C7: 0
A8: Total Project Costs | B8: =SUM(B6:B7) -> 0 | C8: =SUM(C6:C7) -> 0
A10: Non-Construction
A11: Cost Classification | B11: Proposed | C11: Approved
A12: Personnel | B12: =SUMIF(Detail!$C:$C,$A12,Detail!$D:$D) -> 0 | C12: =SUMIF(Detail!$C:$C,$A12,Detail!$D:$D) -> 0
A13: Fringe Benefit | B13: =SUMIF(Detail!$C:$C,$A13,Detail!$D:$D) -> 0 | C13: =SUMIF(Detail!$C:$C,$A13,Detail!$D:$D) -> 0
A14: Travel | B14: =SUMIF(Detail!$C:$C,$A14,Detail!$D:$D) -> 0 | C14: =SUMIF(Detail!$C:$C,$A14,Detail!$D:$D) -> 0
A15: Equipment | B15: =SUMIF(Detail!$C:$C,$A15,Detail!$D:$D) -> 0 | C15: =SUMIF(Detail!$C:$C,$A15,Detail!$D:$D) -> 0
A16: Supplies | B16: =SUMIF(Detail!$C:$C,$A16,Detail!$D:$D) -> 0 | C16: =SUMIF(Detail!$C:$C,$A16,Detail!$D:$D) -> 0
A17: Contractual | B17: =SUMIF(Detail!$C:$C,$A17,Detail!$D:$D) -> 0 | C17: =SUMIF(Detail!$C:$C,$A17,Detail!$D:$D) -> 0
A18: Construction | B18: =SUMIF(Detail!$C:$C,$A18,Detail!$D:$D) -> 0 | C18: =SUMIF(Detail!$C:$C,$A18,Detail!$D:$D) -> 0
A19: Other | B19: =SUMIF(Detail!$C:$C,$A19,Detail!$D:$D) -> 0 | C19: =SUMIF(Detail!$C:$C,$A19,Detail!$D:$D) -> 0
A20: Indirect Charges | B20: =SUMIF(Detail!$C:$C,$A20,Detail!$D:$D) -> 0 | C20: =SUMIF(Detail!$C:$C,$A20,Detail!$D:$D) -> 0
A21: Total Project Costs | B21: =SUM(B12:B20) -> 0 | C21: =SUM(C12:C20) -> 0
